cls/__init__.py
cls/cls.py
cls_clear-1.0.3.dist-info/licenses/LICENSE.txt
cls_clear-1.0.3.dist-info/METADATA
cls_clear-1.0.3.dist-info/WHEEL
cls_clear-1.0.3.dist-info/top_level.txt
cls_clear-1.0.3.dist-info/RECORD
