Metadata-Version: 2.4
Name: cls-clear
Version: 1.0.3
Summary: A simple program to clear the console screen.
Author: Riccardo Belli
License-Expression: Unlicense
Project-URL: Documentation, https://github.com/belliriccardo/cls-clear#readme
Project-URL: Issues, https://github.com/belliriccardo/cls-clear/issues
Project-URL: Source, https://github.com/belliriccardo/cls-clear
Project-URL: Homepage, https://github.com/belliriccardo/cls-clear
Project-URL: Personal Homepage, https://www.riccardobelli.it
Keywords: python,cls,clear,cls-clear,console,screen,clear-screen,terminal,command-line
Classifier: Programming Language :: Python
Classifier: Programming Language :: Python :: 3
Classifier: Programming Language :: Python :: Implementation :: CPython
Classifier: Environment :: Console
Classifier: Typing :: Typed
Classifier: Operating System :: OS Independent
Requires-Python: >=3.0
License-File: LICENSE.txt
Provides-Extra: dev
Requires-Dist: ruff==0.7.4; extra == "dev"
Dynamic: license-file
